scoring_utils/__init__.py
scoring_utils/scoring_utils.py
spread_scoring_utilities-0.1.0.dist-info/LICENSE
spread_scoring_utilities-0.1.0.dist-info/METADATA
spread_scoring_utilities-0.1.0.dist-info/WHEEL
spread_scoring_utilities-0.1.0.dist-info/top_level.txt
spread_scoring_utilities-0.1.0.dist-info/RECORD
